abstract_logs/__init__.py
abstract_logs/abstract_logs.py
abstract_logs/main.py
abstract_logs-0.0.0.4.dist-info/METADATA
abstract_logs-0.0.0.4.dist-info/WHEEL
abstract_logs-0.0.0.4.dist-info/top_level.txt
abstract_logs-0.0.0.4.dist-info/RECORD
